setup.py
logtimer/__init__.py
logtimer.egg-info/PKG-INFO
logtimer.egg-info/SOURCES.txt
logtimer.egg-info/dependency_links.txt
logtimer.egg-info/top_level.txt