Metadata-Version: 1.0
Name: logtimer
Version: 0.1.0
Summary: Times run time of sub steps.
Home-page: UNKNOWN
Author: UNKNOWN
Author-email: UNKNOWN
License: UNKNOWN
Platform: UNKNOWN
